Metadata-Version: 1.1
Name: df2markov
Version: 0.1
Summary: A simple way to create markov chains from dataframes
Home-page: https://github.com/uvacw/df2markov
Author: Susan Vermeer and Damian Trilling
Author-email: s.a.m.vermeer@uva.nl
License: UNKNOWN
Keywords: markov chain,timestamped data,social science
Platform: UNKNOWN
Classifier: Development Status :: 3 - Alpha
Classifier: Intended Audience :: Science/Research
Classifier: License :: OSI Approved :: GNU General Public License v3 (GPLv3)
Classifier: Topic :: Scientific/Engineering
Classifier: Topic :: Sociology
Classifier: Programming Language :: Python :: 3
